linklink/__init__.py
linklink/test.py
linklink-0.0.0.dist-info/METADATA
linklink-0.0.0.dist-info/WHEEL
linklink-0.0.0.dist-info/top_level.txt
linklink-0.0.0.dist-info/RECORD
